[
    {
        "id": 1,
        "semanas": [
            {
                "dias": [
                    {
                        "dia": "Segunda",
                        "evento": "Reunião"
                    },
                    {
                        "dia": "Terça",
                        "evento": "Almoço com cliente"
                    },
                    {
                        "dia": "Quarta",
                        "evento": "Treinamento"
                    },
                    {
                        "dia": "Quinta",
                        "evento": "Projeto X"
                    },
                    {
                        "dia": "Sexta",
                        "evento": "Relatório semanal"
                    },
                    {
                        "dia": "Sábado",
                        "evento": "Desenvolvimento pessoal"
                    },
                    {
                        "dia": "Domingo",
                        "evento": "Descanso"
                    }
                ]
            },
            {
                "dias": [
                    {
                        "dia": "Segunda",
                        "evento": "Reunião"
                    },
                    {
                        "dia": "Terça",
                        "evento": "Treinamento"
                    },
                    {
                        "dia": "Quarta",
                        "evento": "Projeto Y"
                    },
                    {
                        "dia": "Quinta",
                        "evento": "Almoço com cliente"
                    },
                    {
                        "dia": "Sexta",
                        "evento": "Relatório semanal"
                    },
                    {
                        "dia": "Sábado",
                        "evento": "Academia"
                    },
                    {
                        "dia": "Domingo",
                        "evento": "Descanso"
                    }
                ]
            },
            {
                "dias": [
                    {
                        "dia": "Segunda",
                        "evento": "Reunião"
                    },
                    {
                        "dia": "Terça",
                        "evento": "Projeto Z"
                    },
                    {
                        "dia": "Quarta",
                        "evento": "Almoço com cliente"
                    },
                    {
                        "dia": "Quinta",
                        "evento": "Projeto X"
                    },
                    {
                        "dia": "Sexta",
                        "evento": "Relatório semanal"
                    },
                    {
                        "dia": "Sábado",
                        "evento": "Desenvolvimento pessoal"
                    },
                    {
                        "dia": "Domingo",
                        "evento": "Descanso"
                    }
                ]
            },
            {
                "dias": [
                    {
                        "dia": "Segunda",
                        "evento": "Reunião"
                    },
                    {
                        "dia": "Terça",
                        "evento": "Projeto Y"
                    },
                    {
                        "dia": "Quarta",
                        "evento": "Treinamento"
                    },
                    {
                        "dia": "Quinta",
                        "evento": "Projeto X"
                    },
                    {
                        "dia": "Sexta",
                        "evento": "Relatório mensal"
                    },
                    {
                        "dia": "Sábado",
                        "evento": "Academia"
                    },
                    {
                        "dia": "Domingo",
                        "evento": "Descanso"
                    }
                ]
            }
        ]
    }
]